Vectorial.py
Vectorial-1.0.0.dist-info/LICENSE
Vectorial-1.0.0.dist-info/METADATA
Vectorial-1.0.0.dist-info/WHEEL
Vectorial-1.0.0.dist-info/top_level.txt
Vectorial-1.0.0.dist-info/RECORD
