Metadata-Version: 2.1
Name: Vectorial
Version: 1.0.0
Summary: A vector module
Home-page: https://github.com/jonathasgouv/pyvector
Author: Jônathas Gouveia
Author-email: jonathas_gouv@hotmail.com
License: UNKNOWN
Platform: UNKNOWN
Classifier: Programming Language :: Python :: 3
Classifier: License :: OSI Approved :: MIT License
Classifier: Operating System :: OS Independent
